cythonizer/__init__.py
cythonizer/__main__.py
cythonizer-1.2.0b3.dist-info/LICENSE.txt
cythonizer-1.2.0b3.dist-info/METADATA
cythonizer-1.2.0b3.dist-info/WHEEL
cythonizer-1.2.0b3.dist-info/entry_points.txt
cythonizer-1.2.0b3.dist-info/top_level.txt
cythonizer-1.2.0b3.dist-info/RECORD
