Metadata-Version: 2.1
Name: cythonizer
Version: 1.2.0b3
Summary: Convert .py and .pyx to (.pyd | .so) very easily.
Home-page: https://github.com/TechLearnersInc/cythonizer
Author: Rizwan Hasan
Author-email: rizwan.hasan486@gmail.com
License: MIT
Project-URL: Source, https://github.com/TechLearnersInc/cythonizer
Project-URL: Tracker, https://github.com/TechLearnersInc/cythonizer/issues
Project-URL: Facebook, https://www.facebook.com/TechLearnersInc
Project-URL: Linkedin, https://www.linkedin.com/company/techlearners/
Project-URL: Telegram, https://t.me/TechLearners
Keywords: cython cythonizer
Platform: UNKNOWN
Classifier: Development Status :: 4 - Beta
Classifier: Environment :: Console
Classifier: Intended Audience :: Developers
Classifier: Intended Audience :: Science/Research
Classifier: Topic :: Software Development :: Build Tools
Classifier: Programming Language :: Cython
Classifier: License :: OSI Approved :: MIT License
Classifier: Programming Language :: Python :: 3
Classifier: Programming Language :: Python :: 3.6
Classifier: Programming Language :: Python :: 3.7
Classifier: Programming Language :: Python :: 3.8
Classifier: Topic :: Software Development :: Build Tools
Requires-Python: >=3.6
Requires-Dist: cython
Requires-Dist: numpy
